README.md
setup.cfg
setup.py
MD6/__init__.py
MD6/constants.py
MD6/hash/__init__.py
MD6/hash/calc.py
MD6/hash/generator.py
MD6/hash/hash.py
pymd6.egg-info/PKG-INFO
pymd6.egg-info/SOURCES.txt
pymd6.egg-info/dependency_links.txt
pymd6.egg-info/top_level.txt