Metadata-Version: 2.1
Name: pymd6
Version: 0.1.0
Summary: Simple library to calculate MD6 checksum
Home-page: https://github.com/PockusaevAndrey/pymd6
Author: Pokusaev Andrey
Author-email: pockusaevandrey@yandex.ru
License: MIT
Keywords: MD6
Platform: UNKNOWN
Classifier: Development Status :: 5 - Production/Stable
Classifier: Intended Audience :: Developers
Classifier: Topic :: Software Development :: Build Tools
Classifier: License :: OSI Approved :: MIT License
Classifier: Programming Language :: Python :: 3
